<?xml version="1.0" encoding="UTF-8"?>
<foxml:digitalObject VERSION="1.1" PID="islandora:3"
xmlns:foxml="info:fedora/fedora-system:def/foxml#"
xmlns:xsi="http://www.w3.org/2001/XMLSchema-instance"
xsi:schemaLocation="info:fedora/fedora-system:def/foxml# http://www.fedora.info/definitions/1/0/foxml1-1.xsd">
<foxml:objectProperties>
<foxml:property NAME="info:fedora/fedora-system:def/model#state" VALUE="Active"/>
<foxml:property NAME="info:fedora/fedora-system:def/model#label" VALUE="Test object"/>
<foxml:property NAME="info:fedora/fedora-system:def/model#ownerId" VALUE="admin"/>
<foxml:property NAME="info:fedora/fedora-system:def/model#createdDate" VALUE="2018-09-15T02:14:44.093Z"/>
<foxml:property NAME="info:fedora/fedora-system:def/view#lastModifiedDate" VALUE="2018-09-27T12:09:21.033Z"/>
</foxml:objectProperties>
<foxml:datastream ID="AUDIT" STATE="A" CONTROL_GROUP="X" VERSIONABLE="false">
<foxml:datastreamVersion ID="AUDIT.0" LABEL="Audit Trail for this object" CREATED="2018-09-15T02:14:44.093Z" MIMETYPE="text/xml" FORMAT_URI="info:fedora/fedora-system:format/xml.fedora.audit">
<foxml:xmlContent>
<audit:auditTrail xmlns:audit="info:fedora/fedora-system:def/audit#">
<audit:record ID="AUDREC1">
<audit:process type="Fedora API-M"/>
<audit:action>addDatastream</audit:action>
<audit:componentID>TECHMD</audit:componentID>
<audit:responsibility>admin</audit:responsibility>
<audit:date>2018-09-15T02:15:08.533Z</audit:date>
<audit:justification></audit:justification>
</audit:record>
<audit:record ID="AUDREC2">
<audit:process type="Fedora API-M"/>
<audit:action>addDatastream</audit:action>
<audit:componentID>TN</audit:componentID>
<audit:responsibility>admin</audit:responsibility>
<audit:date>2018-09-15T02:15:09.290Z</audit:date>
<audit:justification></audit:justification>
</audit:record>
<audit:record ID="AUDREC3">
<audit:process type="Fedora API-M"/>
<audit:action>addDatastream</audit:action>
<audit:componentID>MEDIUM_SIZE</audit:componentID>
<audit:responsibility>admin</audit:responsibility>
<audit:date>2018-09-15T02:15:10.183Z</audit:date>
<audit:justification></audit:justification>
</audit:record>
<audit:record ID="AUDREC4">
<audit:process type="Fedora API-M"/>
<audit:action>modifyObject</audit:action>
<audit:componentID></audit:componentID>
<audit:responsibility>admin</audit:responsibility>
<audit:date>2018-09-15T14:29:03.684Z</audit:date>
<audit:justification>PREMIS:file=islandora:3+OBJ+OBJ.0; PREMIS:eventType=fixity check; PREMIS:eventOutcome=SHA-1 checksum validated.</audit:justification>
</audit:record>
<audit:record ID="AUDREC5">
<audit:process type="Fedora API-M"/>
<audit:action>modifyDatastreamByReference</audit:action>
<audit:componentID>MODS</audit:componentID>
<audit:responsibility>admin</audit:responsibility>
<audit:date>2018-09-15T14:41:11.061Z</audit:date>
<audit:justification></audit:justification>
</audit:record>
<audit:record ID="AUDREC6">
<audit:process type="Fedora API-M"/>
<audit:action>modifyDatastreamByValue</audit:action>
<audit:componentID>DC</audit:componentID>
<audit:responsibility>admin</audit:responsibility>
<audit:date>2018-09-15T14:41:11.548Z</audit:date>
<audit:justification></audit:justification>
</audit:record>
<audit:record ID="AUDREC7">
<audit:process type="Fedora API-M"/>
<audit:action>modifyObject</audit:action>
<audit:componentID></audit:componentID>
<audit:responsibility>admin</audit:responsibility>
<audit:date>2018-09-18T03:05:41.148Z</audit:date>
<audit:justification>PREMIS:file=islandora:3+OBJ+OBJ.0; PREMIS:eventType=fixity check; PREMIS:eventOutcome=SHA-1 checksum validated.</audit:justification>
</audit:record>
<audit:record ID="AUDREC8">
<audit:process type="Fedora API-M"/>
<audit:action>modifyObject</audit:action>
<audit:componentID></audit:componentID>
<audit:responsibility>admin</audit:responsibility>
<audit:date>2018-09-19T01:38:02.136Z</audit:date>
<audit:justification>PREMIS:file=islandora:3+OBJ+OBJ.0; PREMIS:eventType=fixity check; PREMIS:eventOutcome=SHA-1 checksum validated.</audit:justification>
</audit:record>
<audit:record ID="AUDREC9">
<audit:process type="Fedora API-M"/>
<audit:action>addDatastream</audit:action>
<audit:componentID>MADS</audit:componentID>
<audit:responsibility>admin</audit:responsibility>
<audit:date>2018-09-19T01:44:40.748Z</audit:date>
<audit:justification></audit:justification>
</audit:record>
<audit:record ID="AUDREC10">
<audit:process type="Fedora API-M"/>
<audit:action>purgeDatastream</audit:action>
<audit:componentID>TECHMD</audit:componentID>
<audit:responsibility>admin</audit:responsibility>
<audit:date>2018-09-19T01:55:34.842Z</audit:date>
<audit:justification>Purged datastream (ID=TECHMD), versions ranging from the beginning of time to the end of time.  This resulted in the permanent removal of 1 datastream version(s) (2018-09-15T02:15:08.533Z) and all associated audit records.</audit:justification>
</audit:record>
<audit:record ID="AUDREC11">
<audit:process type="Fedora API-M"/>
<audit:action>addDatastream</audit:action>
<audit:componentID>TECHMD</audit:componentID>
<audit:responsibility>admin</audit:responsibility>
<audit:date>2018-09-19T01:59:42.462Z</audit:date>
<audit:justification></audit:justification>
</audit:record>
<audit:record ID="AUDREC12">
<audit:process type="Fedora API-M"/>
<audit:action>modifyObject</audit:action>
<audit:componentID></audit:componentID>
<audit:responsibility>admin</audit:responsibility>
<audit:date>2018-09-27T12:09:21.033Z</audit:date>
<audit:justification>PREMIS:file=islandora:3+OBJ+OBJ.0; PREMIS:eventType=fixity check; PREMIS:eventOutcome=SHA-1 checksum validated.</audit:justification>
</audit:record>
</audit:auditTrail>
</foxml:xmlContent>
</foxml:datastreamVersion>
</foxml:datastream>
<foxml:datastream ID="RELS-EXT" STATE="A" CONTROL_GROUP="X" VERSIONABLE="true">
<foxml:datastreamVersion ID="RELS-EXT.0" LABEL="Fedora Object to Object Relationship Metadata." CREATED="2018-09-15T02:14:44.093Z" MIMETYPE="application/rdf+xml" FORMAT_URI="info:fedora/fedora-system:FedoraRELSExt-1.0" SIZE="565">
<foxml:contentDigest TYPE="SHA-1" DIGEST="514c6eee7920924a062e30b5a667ae9b0976532a"/>
<foxml:xmlContent>
<rdf:RDF xmlns:rdf="http://www.w3.org/1999/02/22-rdf-syntax-ns#" xmlns:fedora="info:fedora/fedora-system:def/relations-external#" xmlns:fedora-model="info:fedora/fedora-system:def/model#" xmlns:islandora="http://islandora.ca/ontology/relsext#">
  <rdf:Description rdf:about="info:fedora/islandora:3">
    <fedora:isMemberOfCollection rdf:resource="info:fedora/islandora:sp_basic_image_collection"></fedora:isMemberOfCollection>
    <fedora-model:hasModel rdf:resource="info:fedora/islandora:sp_basic_image"></fedora-model:hasModel>
  </rdf:Description>
</rdf:RDF>
</foxml:xmlContent>
</foxml:datastreamVersion>
</foxml:datastream>
<foxml:datastream ID="MODS" STATE="A" CONTROL_GROUP="M" VERSIONABLE="true">
<foxml:datastreamVersion ID="MODS.0" LABEL="MODS Record" CREATED="2018-09-15T02:14:44.093Z" MIMETYPE="application/xml" SIZE="1260">
<foxml:contentDigest TYPE="SHA-1" DIGEST="ac2ea1aeebfe36b1d14afa055d2e02afcd035526"/>
<foxml:contentLocation TYPE="INTERNAL_ID" REF="http://localhost:8080/fedora/get/islandora:3/MODS/2018-09-15T02:14:44.093Z"/>
</foxml:datastreamVersion>
<foxml:datastreamVersion ID="MODS.1" LABEL="MODS Record" CREATED="2018-09-15T14:41:11.061Z" MIMETYPE="application/xml" SIZE="1499">
<foxml:contentDigest TYPE="SHA-1" DIGEST="ee2091430d042520843db4c4397ccf0c65c2361b"/>
<foxml:contentLocation TYPE="INTERNAL_ID" REF="http://localhost:8080/fedora/get/islandora:3/MODS/2018-09-15T14:41:11.061Z"/>
</foxml:datastreamVersion>
</foxml:datastream>
<foxml:datastream ID="DC" STATE="A" CONTROL_GROUP="X" VERSIONABLE="true">
<foxml:datastreamVersion ID="DC.0" LABEL="DC Record" CREATED="2018-09-15T02:14:44.093Z" MIMETYPE="text/xml" SIZE="453">
<foxml:contentDigest TYPE="SHA-1" DIGEST="48978ab8663b483500f192f57cc19b6bdf11517c"/>
<foxml:xmlContent>
<oai_dc:dc xmlns:oai_dc="http://www.openarchives.org/OAI/2.0/oai_dc/" xmlns:dc="http://purl.org/dc/elements/1.1/" xmlns:xsi="http://www.w3.org/2001/XMLSchema-instance" xsi:schemaLocation="http://www.openarchives.org/OAI/2.0/oai_dc/ http://www.openarchives.org/OAI/2.0/oai_dc.xsd">
  <dc:title>Test object</dc:title>
  <dc:type>StillImage</dc:type>
  <dc:format>nonprojected graphic</dc:format>
  <dc:identifier>islandora:3</dc:identifier>
</oai_dc:dc>
</foxml:xmlContent>
</foxml:datastreamVersion>
<foxml:datastreamVersion ID="DC.1" LABEL="DC Record" CREATED="2018-09-15T14:41:11.548Z" MIMETYPE="text/xml" SIZE="453">
<foxml:contentDigest TYPE="SHA-1" DIGEST="48978ab8663b483500f192f57cc19b6bdf11517c"/>
<foxml:xmlContent>
<oai_dc:dc xmlns:dc="http://purl.org/dc/elements/1.1/" xmlns:oai_dc="http://www.openarchives.org/OAI/2.0/oai_dc/" xmlns:xsi="http://www.w3.org/2001/XMLSchema-instance" xsi:schemaLocation="http://www.openarchives.org/OAI/2.0/oai_dc/ http://www.openarchives.org/OAI/2.0/oai_dc.xsd">
  <dc:title>Test object</dc:title>
  <dc:type>StillImage</dc:type>
  <dc:format>nonprojected graphic</dc:format>
  <dc:identifier>islandora:3</dc:identifier>
</oai_dc:dc>
</foxml:xmlContent>
</foxml:datastreamVersion>
</foxml:datastream>
<foxml:datastream ID="OBJ" STATE="A" CONTROL_GROUP="M" VERSIONABLE="true">
<foxml:datastreamVersion ID="OBJ.0" LABEL="pkp_pn_nodes.png" CREATED="2018-09-15T02:14:44.093Z" MIMETYPE="image/png" SIZE="390096">
<foxml:contentDigest TYPE="SHA-1" DIGEST="20c2a5530e8ba09a26fc1878f890440f187db7d0"/>
<foxml:contentLocation TYPE="INTERNAL_ID" REF="http://localhost:8080/fedora/get/islandora:3/OBJ/2018-09-15T02:14:44.093Z"/>
</foxml:datastreamVersion>
</foxml:datastream>
<foxml:datastream ID="TN" STATE="A" CONTROL_GROUP="M" VERSIONABLE="true">
<foxml:datastreamVersion ID="TN.0" LABEL="TN" CREATED="2018-09-15T02:15:09.290Z" MIMETYPE="image/png" SIZE="29216">
<foxml:contentDigest TYPE="SHA-1" DIGEST="49045d803834fa44ec62df6b233db4b3ba85efdc"/>
<foxml:contentLocation TYPE="INTERNAL_ID" REF="http://localhost:8080/fedora/get/islandora:3/TN/2018-09-15T02:15:09.290Z"/>
</foxml:datastreamVersion>
</foxml:datastream>
<foxml:datastream ID="MEDIUM_SIZE" STATE="A" CONTROL_GROUP="M" VERSIONABLE="true">
<foxml:datastreamVersion ID="MEDIUM_SIZE.0" LABEL="MEDIUM_SIZE" CREATED="2018-09-15T02:15:10.183Z" MIMETYPE="image/png" SIZE="149910">
<foxml:contentDigest TYPE="SHA-1" DIGEST="4aaeadb502a42ba34cbabc7bdb228d42ec2b21fb"/>
<foxml:contentLocation TYPE="INTERNAL_ID" REF="http://localhost:8080/fedora/get/islandora:3/MEDIUM_SIZE/2018-09-15T02:15:10.183Z"/>
</foxml:datastreamVersion>
</foxml:datastream>
<foxml:datastream ID="MADS" STATE="A" CONTROL_GROUP="M" VERSIONABLE="true">
<foxml:datastreamVersion ID="MADS.0" LABEL="Mads blah" CREATED="2018-09-19T01:44:40.748Z" MIMETYPE="text/plain" SIZE="8">
<foxml:contentDigest TYPE="SHA-1" DIGEST="c45cb86d7d0572c9714e192b0f5f14759fca1db8"/>
<foxml:contentLocation TYPE="INTERNAL_ID" REF="http://localhost:8080/fedora/get/islandora:3/MADS/2018-09-19T01:44:40.748Z"/>
</foxml:datastreamVersion>
</foxml:datastream>
<foxml:datastream ID="TECHMD" STATE="A" CONTROL_GROUP="M" VERSIONABLE="true">
<foxml:datastreamVersion ID="TECHMD.0" LABEL="TECHMD" CREATED="2018-09-19T01:59:42.462Z" MIMETYPE="application/xml" SIZE="4321">
<foxml:contentDigest TYPE="SHA-1" DIGEST="bbe1794a3d3b1a425b84f0d74c2757ae33b3d553"/>
<foxml:contentLocation TYPE="INTERNAL_ID" REF="http://localhost:8080/fedora/get/islandora:3/TECHMD/2018-09-19T01:59:42.462Z"/>
</foxml:datastreamVersion>
</foxml:datastream>
</foxml:digitalObject>